easy_colors.py
easy_colors-0.0.1.dist-info/LICENSE.txt
easy_colors-0.0.1.dist-info/METADATA
easy_colors-0.0.1.dist-info/WHEEL
easy_colors-0.0.1.dist-info/top_level.txt
easy_colors-0.0.1.dist-info/RECORD
