Metadata-Version: 2.1
Name: easy-colors
Version: 0.0.1
Summary: Colored text in the console
Home-page: https://github.com/farhadzaidi/easy_colors
Author: Farhad Zaidi
Author-email: zaidi.farhad03@gmail.com
License: UNKNOWN
Platform: UNKNOWN
Classifier: Programming Language :: Python :: 3.6
Classifier: Programming Language :: Python :: 3.7
Classifier: Programming Language :: Python :: 3.8
Classifier: License :: OSI Approved :: GNU General Public License v2 or later (GPLv2+)
Classifier: Operating System :: OS Independent
